automation_framework/__init__.py
automation_framework/cli.py
automation_framework/config/__init__.py
automation_framework/config/config.py
automation_framework/pages/__init__.py
automation_framework/pages/base_page.py
automation_framework/utils/__init__.py
automation_framework/utils/api_helper.py
automation_framework/utils/aws_helper.py
automation_framework/utils/db_helper.py
automation_framework/utils/playwright_wrapper.py
automation_testing_framework-0.1.0.dist-info/licenses/LICENSE
config/__init__.py
config/config.py
pages/__init__.py
pages/base_page.py
pages/main_page/__init__.py
pages/main_page/main_page.py
utils/__init__.py
utils/api_helper.py
utils/aws_helper.py
utils/db_helper.py
utils/playwright_wrapper.py
automation_testing_framework-0.1.0.dist-info/METADATA
automation_testing_framework-0.1.0.dist-info/WHEEL
automation_testing_framework-0.1.0.dist-info/entry_points.txt
automation_testing_framework-0.1.0.dist-info/top_level.txt
automation_testing_framework-0.1.0.dist-info/RECORD
