Metadata-Version: 2.4
Name: automation-testing-framework
Version: 0.1.0
Summary: A comprehensive and modular Python-based testing framework for automating API, UI, database, and AWS integration tests
Home-page: https://github.com/udisamuel/automation_framework
Author: Udi Samuel
Author-email: udisamuel@example.com
Project-URL: Bug Tracker, https://github.com/udisamuel/automation_framework/issues
Project-URL: Documentation, https://github.com/udisamuel/automation_framework/docs
Classifier: Programming Language :: Python :: 3
Classifier: Programming Language :: Python :: 3.11
Classifier: License :: OSI Approved :: MIT License
Classifier: Operating System :: OS Independent
Classifier: Topic :: Software Development :: Testing
Classifier: Topic :: Software Development :: Quality Assurance
Classifier: Framework :: Pytest
Requires-Python: >=3.11
License-File: LICENSE
Requires-Dist: pytest~=8.3.5
Requires-Dist: playwright~=1.51.0
Requires-Dist: pytest-playwright~=0.3.0
Requires-Dist: allure-pytest~=2.14.0
Requires-Dist: pytest-xdist~=3.5.0
Requires-Dist: requests~=2.31.0
Requires-Dist: python-dotenv~=1.0.0
Requires-Dist: psycopg2-binary~=2.9.9
Requires-Dist: clickhouse-driver~=0.2.6
Requires-Dist: boto3~=1.34.71
Requires-Dist: botocore~=1.34.71
Dynamic: author
Dynamic: author-email
Dynamic: classifier
Dynamic: description
Dynamic: description-content-type
Dynamic: home-page
Dynamic: license-file
Dynamic: project-url
Dynamic: requires-dist
Dynamic: requires-python
Dynamic: summary
